onyx/__init__.py
onyx/api.py
onyx/cli.py
onyx/config.py
onyx/core.py
onyx/endpoints.py
onyx/exceptions.py
onyx/field.py
climb_onyx_client-4.9.0.dist-info/METADATA
climb_onyx_client-4.9.0.dist-info/WHEEL
climb_onyx_client-4.9.0.dist-info/entry_points.txt
climb_onyx_client-4.9.0.dist-info/licenses/LICENSE
climb_onyx_client-4.9.0.dist-info/RECORD
