Metadata-Version: 2.4
Name: climb-onyx-client
Version: 4.9.0
Summary: CLI and Python library for Onyx
Project-URL: GitHub, https://github.com/CLIMB-TRE/onyx-client
Author-email: Thomas Brier <t.o.brier@bham.ac.uk>
Maintainer-email: Thomas Brier <t.o.brier@bham.ac.uk>
License-Expression: MIT
License-File: LICENSE
Keywords: bioinformatics,metadata,onyx
Classifier: Operating System :: OS Independent
Classifier: Programming Language :: Python :: 3.9
Classifier: Programming Language :: Python :: 3.10
Classifier: Programming Language :: Python :: 3.11
Classifier: Programming Language :: Python :: 3.12
Classifier: Programming Language :: Python :: 3.13
Requires-Python: >=3.9
Requires-Dist: click<8.2,>=8.1.7
Requires-Dist: requests<3,>=2.32
Requires-Dist: rich<13.10,>=13.9.4
Requires-Dist: typer<0.13,>=0.12.3
Provides-Extra: dev
Requires-Dist: coverage; extra == 'dev'
Requires-Dist: pytest; extra == 'dev'
Requires-Dist: ruff; extra == 'dev'
Provides-Extra: test
Requires-Dist: coverage; extra == 'test'
Requires-Dist: pytest; extra == 'test'
